{"name":"accountNumber","identifier":"AXHNKUNO4J","description":null,"slotTypeName":"accountNumber","obfuscationSetting":null,"valueElicitationSetting":{"slotCaptureSetting":{"codeHook":null,"captureResponse":null,"captureNextStep":{"sessionAttributes":{},"dialogAction":{"type":"FulfillIntent","suppressNextMessage":null,"slotToElicit":null},"intent":{"name":null,"slots":{}}},"captureConditional":null,"failureResponse":{"messageGroupsList":[{"message":{"ssmlMessage":null,"customPayload":null,"plainTextMessage":{"value":"Invalid account number. Please, enter correct card"},"imageResponseCard":null},"variations":null}],"allowInterrupt":true},"failureNextStep":{"sessionAttributes":{},"dialogAction":{"type":"StartIntent","suppressNextMessage":null,"slotToElicit":null},"intent":{"name":"FallbackIntent","slots":{}}},"failureConditional":null,"elicitationCodeHook":{"enableCodeHookInvocation":true,"invocationLabel":null}},"promptSpecification":{"messageGroupsList":[{"message":{"ssmlMessage":null,"customPayload":null,"plainTextMessage":{"value":"Please, provide account number to receive information"},"imageResponseCard":null},"variations":[{"ssmlMessage":null,"customPayload":null,"plainTextMessage":{"value":"Enter your card number to receive information"},"imageResponseCard":null},{"ssmlMessage":null,"customPayload":null,"plainTextMessage":{"value":"Enter the correct card number to continue"},"imageResponseCard":null}]}],"maxRetries":4,"allowInterrupt":true,"messageSelectionStrategy":"Random","promptAttemptsSpecification":{"Retry2":{"allowedInputTypes":{"allowAudioInput":true,"allowDTMFInput":true},"audioAndDTMFInputSpecification":{"dtmfSpecification":{"maxLength":513,"deletionCharacter":"*","endCharacter":"#","endTimeoutMs":5000},"startTimeoutMs":4000,"audioSpecification":{"maxLengthMs":15000,"endTimeoutMs":640}},"allowInterrupt":true,"textInputSpecification":{"startTimeoutMs":30000}},"Retry3":{"allowedInputTypes":{"allowAudioInput":true,"allowDTMFInput":true},"audioAndDTMFInputSpecification":{"dtmfSpecification":{"maxLength":513,"deletionCharacter":"*","endCharacter":"#","endTimeoutMs":5000},"startTimeoutMs":4000,"audioSpecification":{"maxLengthMs":15000,"endTimeoutMs":640}},"allowInterrupt":true,"textInputSpecification":{"startTimeoutMs":30000}},"Retry1":{"allowedInputTypes":{"allowAudioInput":true,"allowDTMFInput":true},"audioAndDTMFInputSpecification":{"dtmfSpecification":{"maxLength":513,"deletionCharacter":"*","endCharacter":"#","endTimeoutMs":5000},"startTimeoutMs":4000,"audioSpecification":{"maxLengthMs":15000,"endTimeoutMs":640}},"allowInterrupt":true,"textInputSpecification":{"startTimeoutMs":30000}},"Retry4":{"allowedInputTypes":{"allowAudioInput":true,"allowDTMFInput":true},"audioAndDTMFInputSpecification":{"dtmfSpecification":{"maxLength":513,"deletionCharacter":"*","endCharacter":"#","endTimeoutMs":5000},"startTimeoutMs":4000,"audioSpecification":{"maxLengthMs":15000,"endTimeoutMs":640}},"allowInterrupt":true,"textInputSpecification":{"startTimeoutMs":30000}},"Initial":{"allowedInputTypes":{"allowAudioInput":true,"allowDTMFInput":true},"audioAndDTMFInputSpecification":{"dtmfSpecification":{"maxLength":513,"deletionCharacter":"*","endCharacter":"#","endTimeoutMs":5000},"startTimeoutMs":4000,"audioSpecification":{"maxLengthMs":15000,"endTimeoutMs":640}},"allowInterrupt":true,"textInputSpecification":{"startTimeoutMs":30000}}}},"slotConstraint":"Required","defaultValueSpecification":null,"sampleUtterances":null,"waitAndContinueSpecification":null},"multipleValuesSetting":null}